proxyscrape/VERSION
proxyscrape/__init__.py
proxyscrape/errors.py
proxyscrape/integration.py
proxyscrape/proxyscrape.py
proxyscrape/scrapers.py
proxyscrape/shared.py
proxyscrape/stores.py
sriram_proxyscrape-0.4.0.dist-info/LICENSE.txt
sriram_proxyscrape-0.4.0.dist-info/METADATA
sriram_proxyscrape-0.4.0.dist-info/WHEEL
sriram_proxyscrape-0.4.0.dist-info/top_level.txt
sriram_proxyscrape-0.4.0.dist-info/RECORD
