Metadata-Version: 2.1
Name: sriram-proxyscrape
Version: 0.4.0
Summary: A library for retrieving free proxies (HTTP, HTTPS, SOCKS4, SOCKS5).
Home-page: https://github.com/sriramkumar1996/proxyscrape
Author: Sriram Kumar Boinpalli
Author-email: srirambsk1996@gmail.com
License: MIT
Keywords: proxyscrape proxy scrape scraper
Platform: UNKNOWN
Classifier: Development Status :: 4 - Beta
Classifier: Intended Audience :: Developers
Classifier: License :: OSI Approved :: MIT License
Classifier: Natural Language :: English
Classifier: Operating System :: OS Independent
Classifier: Programming Language :: Python :: 2
Classifier: Programming Language :: Python :: 2.7
Classifier: Programming Language :: Python :: 3
Classifier: Programming Language :: Python :: 3.4
Classifier: Programming Language :: Python :: 3.5
Classifier: Programming Language :: Python :: 3.6
Classifier: Programming Language :: Python :: 3.7
Classifier: Programming Language :: Python :: Implementation :: CPython
Classifier: Topic :: Software Development :: Libraries :: Python Modules
Classifier: Topic :: Utilities
Requires-Dist: BeautifulSoup4
Requires-Dist: requests
